TSCC/__init__.py
TSCC/additional_imports/__init__.py
TSCC/additional_imports/gain_folder/__init__.py
TSCC/additional_imports/gain_folder/gain_functions.py
TSCC/additional_imports/gain_folder/utils.py
TSCC/additional_imports/missingpy/__init__.py
TSCC/additional_imports/missingpy/missforest.py
TSCC/additional_imports/missingpy/pairwise_external.py
TSCC/additional_imports/missingpy/utils.py
TSCC/assessment/__init__.py
TSCC/assessment/data_quality_coefficients.py
TSCC/assessment/evaluation_handler.py
TSCC/assessment/model_error_metrics.py
TSCC/correction/__init__.py
TSCC/correction/baseline.py
TSCC/correction/geo_statisticals.py
TSCC/correction/ml.py
TSCC/correction/statistical.py
TSCC/detection/__init__.py
TSCC/detection/baseline.py
TSCC/detection/basics.py
TSCC/detection/ml.py
TSCC/detection/statistical.py
TSCC/exploration/__init__.py
TSCC/exploration/events.py
TSCC/exploration/general.py
TSCC/preprocessing/__init__.py
TSCC/preprocessing/feature_generation.py
TSCC/preprocessing/general.py
TSCC/preprocessing/plausibility_classes.py
TSCC/preprocessing/synthetic_error_generation.py
TSCC-0.0.8.dist-info/METADATA
TSCC-0.0.8.dist-info/WHEEL
TSCC-0.0.8.dist-info/top_level.txt
TSCC-0.0.8.dist-info/RECORD
